wekalib/__init__.py
wekalib/_version.py
wekalib/circular.py
wekalib/exceptions.py
wekalib/signals.py
wekalib/sthreads.py
wekalib/weka_restapi.py
wekalib/wekaapi.py
wekalib/wekacluster.py
wekalib/wekatime.py
wekalib-1.5.0.dist-info/LICENSE.md
wekalib-1.5.0.dist-info/METADATA
wekalib-1.5.0.dist-info/WHEEL
wekalib-1.5.0.dist-info/top_level.txt
wekalib-1.5.0.dist-info/RECORD
